tfpersistentdata/__init__.py
tfpersistentdata/tfpersistentdata.py
tf_persistent_data-1.0.1.dist-info/METADATA
tf_persistent_data-1.0.1.dist-info/WHEEL
tf_persistent_data-1.0.1.dist-info/top_level.txt
tf_persistent_data-1.0.1.dist-info/RECORD
