Metadata-Version: 2.1
Name: tf-persistent-data
Version: 1.0.1
Summary: tf-persistent-data
Author: kkh
Author-email: doggood720@gmail.com
License: MIT
Requires-Dist: tf-encrypts
